LICENSE.txt
MANIFEST.in
README.rst
setup.cfg
setup.py
by_get/__init__.py
by_get/by_get.py
by_get/version.py
by_get.egg-info/PKG-INFO
by_get.egg-info/SOURCES.txt
by_get.egg-info/dependency_links.txt
by_get.egg-info/entry_points.txt
by_get.egg-info/not-zip-safe
by_get.egg-info/requires.txt
by_get.egg-info/top_level.txt
docs/build/html/api.html
docs/build/html/by_get.html
docs/build/html/genindex.html
docs/build/html/help.html
docs/build/html/index.html
docs/build/html/py-modindex.html
docs/build/html/search.html
docs/build/html/searchindex.js
docs/build/html/_modules/index.html
docs/build/html/_modules/by_get/by_get.html
docs/build/html/_sources/api.txt
docs/build/html/_sources/by_get.txt
docs/build/html/_sources/help.txt
docs/build/html/_sources/index.txt
docs/build/html/_sources/samsifter.txt
docs/build/html/_static/basic.css
docs/build/html/_static/comment-bright.png
docs/build/html/_static/comment-close.png
docs/build/html/_static/comment.png
docs/build/html/_static/default.css
docs/build/html/_static/doctools.js
docs/build/html/_static/down-pressed.png
docs/build/html/_static/down.png
docs/build/html/_static/file.png
docs/build/html/_static/jquery.js
docs/build/html/_static/minus.png
docs/build/html/_static/plus.png
docs/build/html/_static/pygments.css
docs/build/html/_static/searchtools.js
docs/build/html/_static/sidebar.js
docs/build/html/_static/underscore.js
docs/build/html/_static/up-pressed.png
docs/build/html/_static/up.png
docs/build/html/_static/websupport.js
docs/source/_static/basic.css