Metadata-Version: 1.1
Name: by-get
Version: 0.1.0
Summary: BY image getter
Home-page: http://pypi.python.org/pypi/by_get/
Author: Florian Aldehoff
Author-email: by_get@biohazardous.de
License: LICENSE.txt
Platform: UNKNOWN
Classifier: Development Status :: 3 - Alpha
Classifier: Environment :: Console
Classifier: Intended Audience :: Information Technology
Classifier: License :: OSI Approved :: GNU General Public License v3 (GPLv3)
Classifier: Natural Language :: English
Classifier: Operating System :: POSIX
Classifier: Programming Language :: Python :: 3 :: Only
Classifier: Topic :: Internet :: WWW/HTTP :: Indexing/Search
